anime_identify-0.1.0.dist-info/METADATA
anime_identify-0.1.0.dist-info/WHEEL
anime_identify-0.1.0.dist-info/licenses/LICENSE
anime_identify/__init__.py
anime_identify-0.1.0.dist-info/RECORD
